{
	"JVM의 메소드 오버로딩 배워보기": "https://www.itworld.co.kr/news/348555",
	"\"공부도 소비도 현명하게\" 대학생을 위한 무료 PC 앱 15선": "https://www.itworld.co.kr/news/348548",
	"윈도우 PC를 위한 비트로커 암호화 완벽 가이드": "https://www.itworld.co.kr/news/348534",
	"글로벌 칼럼 | 엔터프라이즈 기술의 느린 진화": "https://www.itworld.co.kr/news/348527",
	"AMD 라이젠 9000의 초기 성능 논란, 윈도우 11 24H2 업데이트로 해결?": "https://www.itworld.co.kr/news/348513",
	"\"북미 시장 데이터센터 건설 사상 최고치…공실률은 최저치\" CBRE 그룹": "https://www.itworld.co.kr/news/348506",
	"마이크로소프트, 윈도우용 아웃룩 업데이트 예고": "https://www.itworld.co.kr/news/348499",
	"노로그 정책, VPN 선택 시 꼭 알아야 할 개인정보 보호 기준": "https://www.itworld.co.kr/news/348492",
	"애플, 오는 9월 9일 아이폰 16·애플 워치 시리즈 10 등 신제품 공개": "https://www.itworld.co.kr/news/348457",
	"\"일관된 개발 환경 구축과 간소화\" 데브 컨테이너의 활용과 장점": "https://www.itworld.co.kr/news/348429",
	"블로그 | VR 리듬 게임으로 45kg를 성공적으로 감량한 방법": "https://www.itworld.co.kr/news/348415",
	"글로벌 칼럼 | AI 구현에 적용하는 클라우드 시대의 교훈": "https://www.itworld.co.kr/news/348394",
	"\"혁신은 작은 것부터\" 새로운 그래픽 카드 장착 방식 선보인 에이수스": "https://www.itworld.co.kr/news/348387",
	"\"포토샵 안 부럽다\" 페인트닷넷을 전문가처럼 활용하는 5가지 방법": "https://www.itworld.co.kr/news/348380",
	"AI 이미지 생성 도구 미드저니, 일반 공개 및 구독 요금제 발표": "https://www.itworld.co.kr/news/348366",
	"글로벌 칼럼 | 생성형 AI의 한계…점점 멍청해지는 인공지능의 미래": "https://www.itworld.co.kr/news/348359",
	"데이터 과학 판도를 바꾸는 3가지 프로그래밍 언어": "https://www.itworld.co.kr/news/348296",
	"“이이제이” AI 부정행위 막는 AI 탐지기의 한계와 고전적인 방안": "https://www.itworld.co.kr/news/348275"
}